{
  "collectionName": "components_sections_articles",
  "info": {
    "displayName": "Articles"
  },
  "options": {},
  "attributes": {
    "articles": {
      "type": "relation",
      "relation": "oneToMany",
      "target": "api::article.article"
    },
    "title": {
      "type": "string"
    },
    "description": {
      "type": "text"
    },
    "tag": {
      "type": "string"
    },
    "tagIcon": {
      "allowedTypes": [
        "images",
        "files",
        "videos",
        "audios"
      ],
      "type": "media",
      "multiple": false
    }
  }
}
